{
  "contacts": [
    {
      "day": "friday",
      "people": [
        {
          "name": "Christina",
          "phone": "+45 50 27 62 32",
          "signal_link": "sgnl://call/+4550276232"
        },
        {
          "name": "Mathias",
          "phone": "+45 28 89 22 29",
          "signal_link": "sgnl://call/+4528892229"
        }
      ]
    },
    {
      "day": "saturday",
      "people": [
        {
          "name": "Meagan",
          "phone": "+45 53 68 58 46",
          "signal_link": "sgnl://call/+4553685846"
        },
        {
          "name": "Federico",
          "phone": "+45 23 72 20 23",
          "signal_link": "sgnl://call/+4523722023"
        }
      ]
    },
    {
      "day": "saturday-matinée",
      "people": [
        {
          "name": "Meagan",
          "phone": "+45 53 68 58 46",
          "signal_link": "sgnl://call/+4553685846"
        },
        {
          "name": "Federico",
          "phone": "+45 23 72 20 23",
          "signal_link": "sgnl://call/+4523722023"
        }
      ]
    },
    {
      "day": "sunday",
      "people": [
        {
          "name": "Christina",
          "phone": "+45 50 27 62 32",
          "signal_link": "sgnl://call/+4550276232"
        },
        {
          "name": "Mathias",
          "phone": "+45 28 89 22 29",
          "signal_link": "sgnl://call/+4528892229"
        }
      ]
    },
    {
      "day": "sunday-bike",
      "people": [
        {
          "name": "Christina",
          "phone": "+45 50 27 62 32",
          "signal_link": "sgnl://call/+4550276232"
        },
        {
          "name": "Mathias",
          "phone": "+45 28 89 22 29",
          "signal_link": "https://signal.link/call/#key=mgch-bmmh-phxg-sbdg-pzhc-fkhx-mxcz-mzdr"
        }
      ]
    }
  ]
}
